{
  "key": "plugin_content_manager_configuration_components::banner.service-banner",
  "value": {
    "uid": "banner.service-banner",
    "settings": {
      "bulkable": true,
      "filterable": true,
      "searchable": true,
      "pageSize": 10,
      "mainField": "id",
      "defaultSortBy": "id",
      "defaultSortOrder": "ASC"
    },
    "metadatas": {
      "id": {
        "edit": {},
        "list": {
          "label": "id",
          "searchable": false,
          "sortable": false
        }
      },
      "Description": {
        "edit": {
          "label": "Description",
          "description": "",
          "placeholder": "",
          "visible": true,
          "editable": true
        },
        "list": {
          "label": "Description",
          "searchable": false,
          "sortable": false
        }
      },
      "BackgroundImage": {
        "edit": {
          "label": "BackgroundImage",
          "description": "",
          "placeholder": "",
          "visible": true,
          "editable": true
        },
        "list": {
          "label": "BackgroundImage",
          "searchable": false,
          "sortable": false
        }
      },
      "Header": {
        "edit": {
          "label": "Header",
          "description": "",
          "placeholder": "",
          "visible": true,
          "editable": true
        },
        "list": {
          "label": "Header",
          "searchable": true,
          "sortable": true
        }
      }
    },
    "layouts": {
      "list": [
        "id",
        "Header",
        "BackgroundImage"
      ],
      "edit": [
        [
          {
            "name": "Header",
            "size": 6
          }
        ],
        [
          {
            "name": "Description",
            "size": 12
          }
        ],
        [
          {
            "name": "BackgroundImage",
            "size": 6
          }
        ]
      ],
      "editRelations": []
    },
    "isComponent": true
  },
  "type": "object",
  "environment": null,
  "tag": null
}